{"entityData":{"ground_grass_13":{"entityId":"ground_grass_13","entityType":"ground","variationType":"grass","x":0,"y":-32,"rotation":0},"ground_grass_14":{"entityId":"ground_grass_14","entityType":"ground","variationType":"grass","x":32,"y":-32,"rotation":0},"ground_grass_15_":{"entityId":"ground_grass_15_","entityType":"ground","variationType":"grass","x":64,"y":-32,"rotation":0},"ground_grass_16":{"entityId":"ground_grass_16","entityType":"ground","variationType":"grass","x":96,"y":-32,"rotation":0},"platform_17":{"entityId":"platform_17","entityType":"platform","variationType":"","x":128,"y":-96,"rotation":0},"platform_18":{"entityId":"platform_18","entityType":"platform","variationType":"","x":160,"y":-96,"rotation":0},"platform_19":{"entityId":"platform_19","entityType":"platform","variationType":"","x":192,"y":-96,"rotation":0},"platform_21":{"entityId":"platform_21","entityType":"platform","variationType":"","x":256,"y":-64,"rotation":0},"platform_22":{"entityId":"platform_22","entityType":"platform","variationType":"","x":288,"y":-64,"rotation":0},"platform_23":{"entityId":"platform_23","entityType":"platform","variationType":"","x":320,"y":-64,"rotation":0},"spikes_ball_24":{"entityId":"spikes_ball_24","entityType":"spikes","variationType":"ball","x":256,"y":-96,"rotation":0},"platform_25":{"entityId":"platform_25","entityType":"platform","variationType":"","x":288,"y":-192,"rotation":0},"platform_26":{"entityId":"platform_26","entityType":"platform","variationType":"","x":320,"y":-192,"rotation":0},"platform_27":{"entityId":"platform_27","entityType":"platform","variationType":"","x":352,"y":-192,"rotation":0},"platform_28":{"entityId":"platform_28","entityType":"platform","variationType":"","x":384,"y":-192,"rotation":0},"spikes_ball_29":{"entityId":"spikes_ball_29","entityType":"spikes","variationType":"ball","x":352,"y":-224,"rotation":0},"platform_30":{"entityId":"platform_30","entityType":"platform","variationType":"","x":448,"y":-128,"rotation":0},"coin_31":{"entityId":"coin_31","entityType":"coin","variationType":"","x":448,"y":-160,"rotation":0},"platform_32":{"entityId":"platform_32","entityType":"platform","variationType":"","x":576,"y":-160,"rotation":0},"mushroom_33":{"entityId":"mushroom_33","entityType":"mushroom","variationType":"","x":576,"y":-192,"rotation":0},"coin_34":{"entityId":"coin_34","entityType":"coin","variationType":"","x":640,"y":-224,"rotation":0},"coin_35":{"entityId":"coin_35","entityType":"coin","variationType":"","x":672,"y":-224,"rotation":0},"coin_36":{"entityId":"coin_36","entityType":"coin","variationType":"","x":704,"y":-192,"rotation":0},"ground_grass_37":{"entityId":"ground_grass_37","entityType":"ground","variationType":"grass","x":736,"y":-96,"rotation":0},"ground_grass_38":{"entityId":"ground_grass_38","entityType":"ground","variationType":"grass","x":768,"y":-96,"rotation":0},"ground_grass_39":{"entityId":"ground_grass_39","entityType":"ground","variationType":"grass","x":800,"y":-96,"rotation":0},"ground_grass_40":{"entityId":"ground_grass_40","entityType":"ground","variationType":"grass","x":832,"y":-96,"rotation":0},"spikes_up_41":{"entityId":"spikes_up_41","entityType":"spikes","variationType":"up","x":800,"y":-128,"rotation":0},"star_42":{"entityId":"star_42","entityType":"star","variationType":"","x":768,"y":-128,"rotation":0},"ground_grass_43":{"entityId":"ground_grass_43","entityType":"ground","variationType":"grass","x":928,"y":-32,"rotation":0},"ground_grass_44":{"entityId":"ground_grass_44","entityType":"ground","variationType":"grass","x":960,"y":-32,"rotation":0},"ground_grass_45":{"entityId":"ground_grass_45","entityType":"ground","variationType":"grass","x":992,"y":-32,"rotation":0},"ground_grass_46":{"entityId":"ground_grass_46","entityType":"ground","variationType":"grass","x":1024,"y":-32,"rotation":0},"ground_grass_47":{"entityId":"ground_grass_47","entityType":"ground","variationType":"grass","x":1056,"y":-32,"rotation":0},"ground_grass_48":{"entityId":"ground_grass_48","entityType":"ground","variationType":"grass","x":1088,"y":-32,"rotation":0},"ground_grass_49":{"entityId":"ground_grass_49","entityType":"ground","variationType":"grass","x":1120,"y":-32,"rotation":0},"opponent_jumper_50":{"entityId":"opponent_jumper_50","entityType":"opponent","variationType":"jumper","x":1088,"y":-64,"rotation":0},"opponent_jumper_51":{"entityId":"opponent_jumper_51","entityType":"opponent","variationType":"jumper","x":1024,"y":-64,"rotation":0},"opponent_jumper_52":{"entityId":"opponent_jumper_52","entityType":"opponent","variationType":"jumper","x":960,"y":-64,"rotation":0},"ground_grass_53":{"entityId":"ground_grass_53","entityType":"ground","variationType":"grass","x":1152,"y":-32,"rotation":0},"ground_grass_54":{"entityId":"ground_grass_54","entityType":"ground","variationType":"grass","x":1184,"y":-32,"rotation":0},"platform_56":{"entityId":"platform_56","entityType":"platform","variationType":"","x":1152,"y":-192,"rotation":0},"platform_57":{"entityId":"platform_57","entityType":"platform","variationType":"","x":1184,"y":-192,"rotation":0},"platform_58":{"entityId":"platform_58","entityType":"platform","variationType":"","x":1216,"y":-192,"rotation":0},"platform_59":{"entityId":"platform_59","entityType":"platform","variationType":"","x":1216,"y":-192,"rotation":0},"platform_60":{"entityId":"platform_60","entityType":"platform","variationType":"","x":1248,"y":-192,"rotation":0},"platform_61":{"entityId":"platform_61","entityType":"platform","variationType":"","x":1248,"y":-192,"rotation":0},"platform_62":{"entityId":"platform_62","entityType":"platform","variationType":"","x":960,"y":-384,"rotation":0},"platform_63":{"entityId":"platform_63","entityType":"platform","variationType":"","x":992,"y":-384,"rotation":0},"platform_64":{"entityId":"platform_64","entityType":"platform","variationType":"","x":1024,"y":-384,"rotation":0},"platform_65":{"entityId":"platform_65","entityType":"platform","variationType":"","x":1024,"y":-384,"rotation":0},"platform_66":{"entityId":"platform_66","entityType":"platform","variationType":"","x":1024,"y":-416,"rotation":0},"platform_67":{"entityId":"platform_67","entityType":"platform","variationType":"","x":1056,"y":-384,"rotation":0},"platform_68":{"entityId":"platform_68","entityType":"platform","variationType":"","x":1056,"y":-384,"rotation":0},"platform_69":{"entityId":"platform_69","entityType":"platform","variationType":"","x":1088,"y":-320,"rotation":0},"spikes_ball_70":{"entityId":"spikes_ball_70","entityType":"spikes","variationType":"ball","x":1024,"y":-448,"rotation":0},"platform_71":{"entityId":"platform_71","entityType":"platform","variationType":"","x":864,"y":-544,"rotation":0},"platform_72":{"entityId":"platform_72","entityType":"platform","variationType":"","x":832,"y":-544,"rotation":0},"platform_73":{"entityId":"platform_73","entityType":"platform","variationType":"","x":800,"y":-544,"rotation":0},"platform_74":{"entityId":"platform_74","entityType":"platform","variationType":"","x":800,"y":-544,"rotation":0},"platform_75":{"entityId":"platform_75","entityType":"platform","variationType":"","x":896,"y":-480,"rotation":0},"opponent_jumper_76":{"entityId":"opponent_jumper_76","entityType":"opponent","variationType":"jumper","x":864,"y":-576,"rotation":0},"platform_77":{"entityId":"platform_77","entityType":"platform","variationType":"","x":992,"y":-640,"rotation":0},"platform_78":{"entityId":"platform_78","entityType":"platform","variationType":"","x":1024,"y":-640,"rotation":0},"platform_79":{"entityId":"platform_79","entityType":"platform","variationType":"","x":1056,"y":-640,"rotation":0},"platform_80":{"entityId":"platform_80","entityType":"platform","variationType":"","x":1088,"y":-640,"rotation":0},"platform_81":{"entityId":"platform_81","entityType":"platform","variationType":"","x":1248,"y":-608,"rotation":0},"platform_82":{"entityId":"platform_82","entityType":"platform","variationType":"","x":1280,"y":-608,"rotation":0},"platform_83":{"entityId":"platform_83","entityType":"platform","variationType":"","x":1312,"y":-608,"rotation":0},"platform_84":{"entityId":"platform_84","entityType":"platform","variationType":"","x":1440,"y":-416,"rotation":0},"spikes_ball_85":{"entityId":"spikes_ball_85","entityType":"spikes","variationType":"ball","x":1472,"y":-416,"rotation":0},"platform_86":{"entityId":"platform_86","entityType":"platform","variationType":"","x":1568,"y":-320,"rotation":0},"platform_87":{"entityId":"platform_87","entityType":"platform","variationType":"","x":1600,"y":-320,"rotation":0},"platform_88":{"entityId":"platform_88","entityType":"platform","variationType":"","x":1632,"y":-320,"rotation":0},"platform_89":{"entityId":"platform_89","entityType":"platform","variationType":"","x":1664,"y":-320,"rotation":0},"ground_grass_90":{"entityId":"ground_grass_90","entityType":"ground","variationType":"grass","x":1664,"y":-64,"rotation":0},"ground_grass_91":{"entityId":"ground_grass_91","entityType":"ground","variationType":"grass","x":1696,"y":-64,"rotation":0},"ground_grass_92":{"entityId":"ground_grass_92","entityType":"ground","variationType":"grass","x":1728,"y":-64,"rotation":0},"ground_grass_93":{"entityId":"ground_grass_93","entityType":"ground","variationType":"grass","x":1760,"y":-64,"rotation":0},"ground_grass_94":{"entityId":"ground_grass_94","entityType":"ground","variationType":"grass","x":1792,"y":-64,"rotation":0},"coin_95":{"entityId":"coin_95","entityType":"coin","variationType":"","x":1792,"y":-96,"rotation":0},"coin_96":{"entityId":"coin_96","entityType":"coin","variationType":"","x":1760,"y":-96,"rotation":0},"coin_97":{"entityId":"coin_97","entityType":"coin","variationType":"","x":1728,"y":-96,"rotation":0},"coin_98":{"entityId":"coin_98","entityType":"coin","variationType":"","x":1664,"y":-96,"rotation":0},"coin_99":{"entityId":"coin_99","entityType":"coin","variationType":"","x":1696,"y":-96,"rotation":0},"ground_grass_100":{"entityId":"ground_grass_100","entityType":"ground","variationType":"grass","x":1824,"y":-32,"rotation":0},"ground_grass_101":{"entityId":"ground_grass_101","entityType":"ground","variationType":"grass","x":1856,"y":-32,"rotation":0},"ground_grass_102":{"entityId":"ground_grass_102","entityType":"ground","variationType":"grass","x":1888,"y":-32,"rotation":0},"ground_grass_103":{"entityId":"ground_grass_103","entityType":"ground","variationType":"grass","x":1920,"y":-32,"rotation":0},"ground_grass_104":{"entityId":"ground_grass_104","entityType":"ground","variationType":"grass","x":1984,"y":-32,"rotation":0},"ground_grass_105":{"entityId":"ground_grass_105","entityType":"ground","variationType":"grass","x":1952,"y":-32,"rotation":0},"ground_grass_106":{"entityId":"ground_grass_106","entityType":"ground","variationType":"grass","x":2016,"y":-32,"rotation":0},"opponent_jumper_107":{"entityId":"opponent_jumper_107","entityType":"opponent","variationType":"jumper","x":1952,"y":-64,"rotation":0},"opponent_jumper_108":{"entityId":"opponent_jumper_108","entityType":"opponent","variationType":"jumper","x":1888,"y":-64,"rotation":0},"star_109":{"entityId":"star_109","entityType":"star","variationType":"","x":1216,"y":-352,"rotation":0},"ground_dirt_110":{"entityId":"ground_dirt_110","entityType":"ground","variationType":"dirt","x":1248,"y":-320,"rotation":0},"ground_grass_111":{"entityId":"ground_grass_111","entityType":"ground","variationType":"grass","x":2048,"y":-32,"rotation":0},"ground_grass_112":{"entityId":"ground_grass_112","entityType":"ground","variationType":"grass","x":2048,"y":-64,"rotation":0},"ground_grass_113":{"entityId":"ground_grass_113","entityType":"ground","variationType":"grass","x":2048,"y":-128,"rotation":0},"ground_grass_114":{"entityId":"ground_grass_114","entityType":"ground","variationType":"grass","x":2048,"y":-96,"rotation":0},"ground_grass_115":{"entityId":"ground_grass_115","entityType":"ground","variationType":"grass","x":2048,"y":-160,"rotation":0},"ground_grass_116":{"entityId":"ground_grass_116","entityType":"ground","variationType":"grass","x":2080,"y":-192,"rotation":0},"ground_grass_117":{"entityId":"ground_grass_117","entityType":"ground","variationType":"grass","x":2080,"y":-160,"rotation":0},"ground_grass_118":{"entityId":"ground_grass_118","entityType":"ground","variationType":"grass","x":2112,"y":-160,"rotation":0},"ground_grass_119":{"entityId":"ground_grass_119","entityType":"ground","variationType":"grass","x":2144,"y":-160,"rotation":0},"ground_grass_120":{"entityId":"ground_grass_120","entityType":"ground","variationType":"grass","x":2176,"y":-160,"rotation":0},"ground_grass_121":{"entityId":"ground_grass_121","entityType":"ground","variationType":"grass","x":2208,"y":-160,"rotation":0},"ground_grass_122":{"entityId":"ground_grass_122","entityType":"ground","variationType":"grass","x":2240,"y":-160,"rotation":0},"ground_grass_123":{"entityId":"ground_grass_123","entityType":"ground","variationType":"grass","x":2272,"y":-160,"rotation":0},"ground_grass_124":{"entityId":"ground_grass_124","entityType":"ground","variationType":"grass","x":2304,"y":-160,"rotation":0},"ground_grass_125":{"entityId":"ground_grass_125","entityType":"ground","variationType":"grass","x":2336,"y":-160,"rotation":0},"ground_grass_126":{"entityId":"ground_grass_126","entityType":"ground","variationType":"grass","x":2368,"y":-160,"rotation":0},"ground_grass_127":{"entityId":"ground_grass_127","entityType":"ground","variationType":"grass","x":2528,"y":-192,"rotation":0},"ground_grass_128":{"entityId":"ground_grass_128","entityType":"ground","variationType":"grass","x":2528,"y":-288,"rotation":0},"ground_grass_129":{"entityId":"ground_grass_129","entityType":"ground","variationType":"grass","x":2528,"y":-256,"rotation":0},"ground_grass_130":{"entityId":"ground_grass_130","entityType":"ground","variationType":"grass","x":2528,"y":-224,"rotation":0},"ground_grass_131":{"entityId":"ground_grass_131","entityType":"ground","variationType":"grass","x":2528,"y":-128,"rotation":0},"ground_grass_132":{"entityId":"ground_grass_132","entityType":"ground","variationType":"grass","x":2528,"y":-96,"rotation":0},"ground_grass_133":{"entityId":"ground_grass_133","entityType":"ground","variationType":"grass","x":2528,"y":-160,"rotation":0},"ground_grass_134":{"entityId":"ground_grass_134","entityType":"ground","variationType":"grass","x":2528,"y":-64,"rotation":0},"ground_grass_135":{"entityId":"ground_grass_135","entityType":"ground","variationType":"grass","x":2496,"y":-64,"rotation":0},"ground_grass_136":{"entityId":"ground_grass_136","entityType":"ground","variationType":"grass","x":2496,"y":-32,"rotation":0},"ground_grass_137":{"entityId":"ground_grass_137","entityType":"ground","variationType":"grass","x":2528,"y":-32,"rotation":0},"ground_grass_138":{"entityId":"ground_grass_138","entityType":"ground","variationType":"grass","x":2464,"y":-32,"rotation":0},"ground_grass_139":{"entityId":"ground_grass_139","entityType":"ground","variationType":"grass","x":2432,"y":-64,"rotation":0},"ground_grass_140":{"entityId":"ground_grass_140","entityType":"ground","variationType":"grass","x":2400,"y":-32,"rotation":0},"ground_grass_141":{"entityId":"ground_grass_141","entityType":"ground","variationType":"grass","x":2432,"y":-32,"rotation":0},"ground_grass_142":{"entityId":"ground_grass_142","entityType":"ground","variationType":"grass","x":2368,"y":-32,"rotation":0},"ground_grass_143":{"entityId":"ground_grass_143","entityType":"ground","variationType":"grass","x":2336,"y":-32,"rotation":0},"ground_grass_144":{"entityId":"ground_grass_144","entityType":"ground","variationType":"grass","x":2336,"y":-32,"rotation":0},"ground_grass_145":{"entityId":"ground_grass_145","entityType":"ground","variationType":"grass","x":2304,"y":-32,"rotation":0},"ground_grass_146":{"entityId":"ground_grass_146","entityType":"ground","variationType":"grass","x":2272,"y":-32,"rotation":0},"ground_grass_147":{"entityId":"ground_grass_147","entityType":"ground","variationType":"grass","x":2240,"y":-32,"rotation":0},"ground_grass_148":{"entityId":"ground_grass_148","entityType":"ground","variationType":"grass","x":2208,"y":-32,"rotation":0},"ground_grass_149":{"entityId":"ground_grass_149","entityType":"ground","variationType":"grass","x":2208,"y":-32,"rotation":0},"ground_grass_150":{"entityId":"ground_grass_150","entityType":"ground","variationType":"grass","x":2176,"y":-64,"rotation":0},"ground_grass_151":{"entityId":"ground_grass_151","entityType":"ground","variationType":"grass","x":2176,"y":-64,"rotation":0},"ground_grass_152":{"entityId":"ground_grass_152","entityType":"ground","variationType":"grass","x":2144,"y":-64,"rotation":0},"ground_grass_153":{"entityId":"ground_grass_153","entityType":"ground","variationType":"grass","x":2112,"y":-64,"rotation":0},"ground_grass_154":{"entityId":"ground_grass_154","entityType":"ground","variationType":"grass","x":2112,"y":-64,"rotation":0},"ground_grass_155":{"entityId":"ground_grass_155","entityType":"ground","variationType":"grass","x":2080,"y":-64,"rotation":0},"ground_grass_156":{"entityId":"ground_grass_156","entityType":"ground","variationType":"grass","x":2080,"y":-32,"rotation":0},"ground_grass_157":{"entityId":"ground_grass_157","entityType":"ground","variationType":"grass","x":2112,"y":-32,"rotation":0},"ground_grass_158":{"entityId":"ground_grass_158","entityType":"ground","variationType":"grass","x":2112,"y":-32,"rotation":0},"ground_grass_159":{"entityId":"ground_grass_159","entityType":"ground","variationType":"grass","x":2144,"y":-32,"rotation":0},"ground_grass_160":{"entityId":"ground_grass_160","entityType":"ground","variationType":"grass","x":2176,"y":-32,"rotation":0},"finish_161":{"entityId":"finish_161","entityType":"finish","variationType":"","x":2080,"y":-96,"rotation":0},"finish_162":{"entityId":"finish_162","entityType":"finish","variationType":"","x":2080,"y":-128,"rotation":0},"opponent_walker_163":{"entityId":"opponent_walker_163","entityType":"opponent","variationType":"walker","x":2400,"y":-64,"rotation":0},"opponent_walker_164":{"entityId":"opponent_walker_164","entityType":"opponent","variationType":"walker","x":2176,"y":-192,"rotation":0},"opponent_jumper_165":{"entityId":"opponent_jumper_165","entityType":"opponent","variationType":"jumper","x":2336,"y":-192,"rotation":0},"spikes_ball_166":{"entityId":"spikes_ball_166","entityType":"spikes","variationType":"ball","x":2400,"y":-160,"rotation":0},"spikes_ball_167":{"entityId":"spikes_ball_167","entityType":"spikes","variationType":"ball","x":2432,"y":-160,"rotation":0},"spikes_ball_168":{"entityId":"spikes_ball_168","entityType":"spikes","variationType":"ball","x":2464,"y":-160,"rotation":0},"platform_169":{"entityId":"platform_169","entityType":"platform","variationType":"","x":2400,"y":-288,"rotation":0},"platform_170":{"entityId":"platform_170","entityType":"platform","variationType":"","x":2432,"y":-288,"rotation":0},"platform_171":{"entityId":"platform_171","entityType":"platform","variationType":"","x":2464,"y":-288,"rotation":0},"ground_grass_172":{"entityId":"ground_grass_172","entityType":"ground","variationType":"grass","x":2528,"y":-320,"rotation":0},"ground_grass_173":{"entityId":"ground_grass_173","entityType":"ground","variationType":"grass","x":2528,"y":-352,"rotation":0},"ground_grass_174":{"entityId":"ground_grass_174","entityType":"ground","variationType":"grass","x":2528,"y":-384,"rotation":0},"ground_grass_175":{"entityId":"ground_grass_175","entityType":"ground","variationType":"grass","x":2528,"y":-416,"rotation":0},"ground_grass_176":{"entityId":"ground_grass_176","entityType":"ground","variationType":"grass","x":2528,"y":-448,"rotation":0},"ground_grass_177":{"entityId":"ground_grass_177","entityType":"ground","variationType":"grass","x":2528,"y":-480,"rotation":0},"ground_grass_178":{"entityId":"ground_grass_178","entityType":"ground","variationType":"grass","x":2528,"y":-512,"rotation":0},"ground_grass_179":{"entityId":"ground_grass_179","entityType":"ground","variationType":"grass","x":2528,"y":-512,"rotation":0},"ground_grass_180":{"entityId":"ground_grass_180","entityType":"ground","variationType":"grass","x":2528,"y":-544,"rotation":0},"ground_grass_181":{"entityId":"ground_grass_181","entityType":"ground","variationType":"grass","x":2528,"y":-576,"rotation":0},"ground_grass_182":{"entityId":"ground_grass_182","entityType":"ground","variationType":"grass","x":2528,"y":-576,"rotation":0},"platform_188":{"entityId":"platform_188","entityType":"platform","variationType":"","x":160,"y":-192,"rotation":0},"platform_189":{"entityId":"platform_189","entityType":"platform","variationType":"","x":192,"y":-192,"rotation":0},"platform_192":{"entityId":"platform_192","entityType":"platform","variationType":"","x":1536,"y":-64,"rotation":0},"platform_193":{"entityId":"platform_193","entityType":"platform","variationType":"","x":1568,"y":-64,"rotation":0}},"editableComponentData":{"Balance":{"accelerationForce":1000,"killJumpForce":420,"maxFallingSpeed":800,"maxSpeed":230,"normalJumpForce":210,"starInvincibilityTime":4000},"OpponentWalker":{"speed":70},"OpponentJumper":{"horizontalJumpForce":40,"verticalJumpForce":510}},"levelMetaData":{"levelName":"2","levelId":5615,"storageLocation":"authorGenerated","lastModificationTime":"周三 5月 16 03:26:57 2018 GMT","creationTime":"周五 5月 11 02:31:29 2018 GMT"},"customData":{"background":0,"playerX":32,"playerY":-96}}